easypostgres/__init__.py
easypostgres/connection.py
easypostgres/mapper.py
pbeasypostgres-0.1.0.dist-info/LICENSE
pbeasypostgres-0.1.0.dist-info/METADATA
pbeasypostgres-0.1.0.dist-info/WHEEL
pbeasypostgres-0.1.0.dist-info/top_level.txt
pbeasypostgres-0.1.0.dist-info/RECORD
