Metadata-Version: 2.1
Name: pbeasypostgres
Version: 0.1.0
Summary: Easy PostgreSQL database adapter for Python based on psycopg2
Author: ig-acc
Author-email: igortalin8@gmail.com
Classifier: Programming Language :: Python :: 3
Classifier: License :: OSI Approved :: MIT License
Classifier: Operating System :: OS Independent
Requires-Python: >=3.10
License-File: LICENSE
Requires-Dist: psycopg2
